green_screen_picture/__init__.py
green_screen_picture/processing/__init__.py
green_screen_picture/processing/combination.py
green_screen_picture/utils/__init__.py
green_screen_picture/utils/io.py
green_screen_picture-0.0.1.dist-info/METADATA
green_screen_picture-0.0.1.dist-info/WHEEL
green_screen_picture-0.0.1.dist-info/top_level.txt
green_screen_picture-0.0.1.dist-info/RECORD
