Metadata-Version: 2.1
Name: green-screen-picture
Version: 0.0.1
Summary: simple package to add background images to green screen
Home-page: https://github.com/mrcs22/green_screen_picture
Author: mrcs22
Author-email: marcusmoraes2010@hotmail.com
License: UNKNOWN
Platform: UNKNOWN
Requires-Python: >=3.8
Requires-Dist: numpy (==1.22.2)
Requires-Dist: scikit-image (==0.19.2)
